ch347/GPIO.py
ch347/I2C.py
ch347/JTAG.py
ch347/SPI.py
ch347/UART.py
ch347/__init__.py
ch347/config.json
ch347/const.py
ch347/core.py
ch347/util.py
CH347-1.0.2.dist-info/METADATA
CH347-1.0.2.dist-info/WHEEL
CH347-1.0.2.dist-info/top_level.txt
CH347-1.0.2.dist-info/RECORD
